<problem display_name="Multiple Choice" markdown="1. PCB is Acronym of ?&#10;(x) Printed Circuit Board&#10;( ) Print Circuit Breaker&#10;( ) Personal Circuit Board&#10;( ) Poly chlorinated biphenyl&#10;&#10;2. Material used in PCB ?&#10;( ) Phynolic Cotton Paper&#10;( ) Woven Glass and Eproxy&#10;( ) Matte Glass and Polyester&#10;(x) All of the above&#10;&#10;3. Board Coated with color ?&#10;(x) Green,Blue and Red&#10;( ) White&#10;( ) Gray&#10;( ) All of the above&#10;&#10;4. Chemical etching can do with ?&#10;( ) Ferric Cloride&#10;( ) Ammonium persulfate&#10;( ) Hydrochloric Acid&#10;(x) All of the Above&#10;&#10;5. Inventor of PCB ?&#10;( ) Neil Eisler&#10;(x) Paul Eisler&#10;( ) Peter Eisler&#10;( ) Thomas Edison">
<p>1. PCB is Acronym of ?</p>
<multiplechoiceresponse>
  <choicegroup type="MultipleChoice">
    <choice correct="true">Printed Circuit Board</choice>
    <choice correct="false">Print Circuit Breaker</choice>
    <choice correct="false">Personal Circuit Board</choice>
    <choice correct="false">Poly chlorinated biphenyl</choice>
  </choicegroup>
</multiplechoiceresponse>

<p>2. Material used in PCB ?</p>
<multiplechoiceresponse>
  <choicegroup type="MultipleChoice">
    <choice correct="false">Phynolic Cotton Paper</choice>
    <choice correct="false">Woven Glass and Eproxy</choice>
    <choice correct="false">Matte Glass and Polyester</choice>
    <choice correct="true">All of the above</choice>
  </choicegroup>
</multiplechoiceresponse>

<p>3. Board Coated with color ?</p>
<multiplechoiceresponse>
  <choicegroup type="MultipleChoice">
    <choice correct="true">Green,Blue and Red</choice>
    <choice correct="false">White</choice>
    <choice correct="false">Gray</choice>
    <choice correct="false">All of the above</choice>
  </choicegroup>
</multiplechoiceresponse>

<p>4. Chemical etching can do with ?</p>
<multiplechoiceresponse>
  <choicegroup type="MultipleChoice">
    <choice correct="false">Ferric Cloride</choice>
    <choice correct="false">Ammonium persulfate</choice>
    <choice correct="false">Hydrochloric Acid</choice>
    <choice correct="true">All of the Above</choice>
  </choicegroup>
</multiplechoiceresponse>

<p>5. Inventor of PCB ?</p>
<multiplechoiceresponse>
  <choicegroup type="MultipleChoice">
    <choice correct="false">Neil Eisler</choice>
    <choice correct="true">Paul Eisler</choice>
    <choice correct="false">Peter Eisler</choice>
    <choice correct="false">Thomas Edison</choice>
  </choicegroup>
</multiplechoiceresponse>


</problem>
